CHANGES.txt
IDEAS.md
LICENCE.txt
MANIFEST.in
README.md
VERSION.txt
requirements.txt
setup.py
bin/jobmanager-ctl
jobmanager/__init__.py
jobmanager/common/__init__.py
jobmanager/common/docker.py
jobmanager/common/example.py
jobmanager/common/example_v2.py
jobmanager/common/host.py
jobmanager/common/job.py
jobmanager/common/test.py
jobmanager_common.egg-info/PKG-INFO
jobmanager_common.egg-info/SOURCES.txt
jobmanager_common.egg-info/dependency_links.txt
jobmanager_common.egg-info/requires.txt
jobmanager_common.egg-info/top_level.txt