Metadata-Version: 1.1
Name: jobmanager-common
Version: 0.13.10
Summary: Job Manager Common Library
Home-page: https://github.com/ronhanson/python-jobmanager-common
Author: Ronan Delacroix
Author-email: ronan.delacroix@gmail.com
License: The MIT License (MIT)
